LICENSE
capablerobot_usbregister/__init__.py
capablerobot_usbregister/binaries/wdi-32bit.exe
capablerobot_usbregister/binaries/wdi-64bit.exe
capablerobot_usbregister/main.py
requirements.txt
capablerobot_usbregister-1.3.2.dist-info/entry_points.txt
capablerobot_usbregister-1.3.2.dist-info/LICENSE
capablerobot_usbregister-1.3.2.dist-info/WHEEL
capablerobot_usbregister-1.3.2.dist-info/METADATA
capablerobot_usbregister-1.3.2.dist-info/RECORD
