Metadata-Version: 2.1
Name: capablerobot-usbregister
Version: 1.3.2
Summary: Windows command line tool to assist in registering USB drivers
Home-page: https://github.com/CapableRobot/CapableRobot_USBRegister
License: MIT
Keywords: usb,hardware
Author: Chris Osterwood
Author-email: osterwood@capablerobot.com
Requires-Python: >=3.6,<4.0
Classifier: License :: OSI Approved :: MIT License
Classifier: Programming Language :: Python :: 3
Classifier: Programming Language :: Python :: 3.6
Classifier: Programming Language :: Python :: 3.7
Classifier: Programming Language :: Python :: 3.8
Classifier: Programming Language :: Python :: 3.9
Requires-Dist: click (>=7.0,<8.0)
Project-URL: Repository, https://github.com/CapableRobot/CapableRobot_USBRegister
